task3/ram.sv
module ram #(
    parameter ADDRESS_WIDTH = 9,
                DATA_WIDTH = 8
) (
    input logic             clk,
    input logic             wr_en,
    input logic             rd_en,
    input logic         [ADDRESS_WIDTH-1:0] wr_addr,
    input logic         [ADDRESS_WIDTH-1:0] rd_addr,  
    input logic        [DATA_WIDTH-1:0] din,
    output logic        [DATA_WIDTH-1:0] dout
);

logic [DATA_WIDTH-1:0] ram_array [2**ADDRESS_WIDTH-1:0];

always_ff @(posedge clk) begin
    if(wr_en == 1'b1)
        ram_array[wr_addr] <= din;
    if(rd_en == 1'b1)
        dout <= ram_array[rd_addr];
end;
endmodule

task3/counter.sv
module counter #(
    parameter WIDTH = 9
)(
    input logic clk,
    input logic rst, 
    input logic en,
    input logic [WIDTH-1:0] incr,
    output logic [WIDTH-1:0] count
);

always @ (posedge clk, posedge rst)
    if (rst)
        count <= {WIDTH{1'b0}};
    else if(en) 
        count <= count + incr;

endmodule

task3/sigdelay.sv
module sigdelay #(
    parameter A_WIDTH = 9,
              D_WIDTH = 8
)(
    input logic     clk,
    input logic     rst,
    input logic     en,
    input logic     wr_en,
    input logic     rd_en,
    input logic [A_WIDTH-1:0] offset,
    input logic [D_WIDTH-1:0] mic_signal,
    output logic [D_WIDTH-1:0] delayed_signal
);

logic [A_WIDTH-1:0] address;

counter counter (
    .clk (clk),
    .rst (rst),
    .en (en),
    .incr (offset),
    .count (address)
);

ram voiceram (
    .clk(clk),
    .rd_en (rd_en),
    .wr_en (wr_en),
    .rd_addr (address),
    .wr_addr (address+incr),
    .din (mic_signal),
    .dout (delayed_signal)
);

endmodule

task3/sigdelay.vcd
$version Generated by VerilatedVcd $end
$date Thu Oct 24 19:51:25 2024 $end
$timescale 1ps $end

 $scope module TOP $end
  $var wire  1 # clk $end
  $var wire  8 * delayed_signal [7:0] $end
  $var wire  1 % en $end
  $var wire  8 ) mic_signal [7:0] $end
  $var wire  9 ( offset [8:0] $end
  $var wire  1 ' rd_en $end
  $var wire  1 $ rst $end
  $var wire  1 & wr_en $end
  $scope module sigdelay $end
   $var wire 32 - A_WIDTH [31:0] $end
   $var wire 32 . D_WIDTH [31:0] $end
   $var wire  9 + address [8:0] $end
   $var wire  1 # clk $end
   $var wire  8 * delayed_signal [7:0] $end
   $var wire  1 % en $end
   $var wire  1 / incr $end
   $var wire  8 ) mic_signal [7:0] $end
   $var wire  9 ( offset [8:0] $end
   $var wire  1 ' rd_en $end
   $var wire  1 $ rst $end
   $var wire  1 & wr_en $end
   $scope module counter $end
    $var wire 32 - WIDTH [31:0] $end
    $var wire  1 # clk $end
    $var wire  9 + count [8:0] $end
    $var wire  1 % en $end
    $var wire  9 ( incr [8:0] $end
    $var wire  1 $ rst $end
   $upscope $end
   $scope module voiceram $end
    $var wire 32 - ADDRESS_WIDTH [31:0] $end
    $var wire 32 . DATA_WIDTH [31:0] $end
    $var wire  1 # clk $end
    $var wire  8 ) din [7:0] $end
    $var wire  8 * dout [7:0] $end
    $var wire  9 + rd_addr [8:0] $end
    $var wire  1 ' rd_en $end
    $var wire  9 , wr_addr [8:0] $end
    $var wire  1 & wr_en $end
   $upscope $end
  $upscope $end
 $upscope $end
$enddefinitions $end


#0
1#
0$
0%
1&
1'
b001000000 (
b00000000 )
b00000000 *
b000000000 +
b000000000 ,
b00000000000000000000000000001001 -
b00000000000000000000000000001000 .
0/
#1
0#
#2
1#
b000110011 (
b01110010 )
#3
0#
#4
1#
b01110001 )
#5
0#
#6
1#
b01101110 )
b01110010 *
#7
0#
#8
1#
b01110001 *
#9
0#
#10
1#
b01101111 )
b01101110 *
#11
0#
#12
1#
b01101100 )
#13
0#
#14
1#
b01101111 )
b01101111 *
#15
0#
#16
1#
b01101100 )
b01101100 *
#17
0#
#18
1#
b01101101 )
b01101111 *
#19
0#
#20
1#
b01101110 )
b01101100 *
#21
0#
#22
1#
b01101111 )
b01101101 *
#23
0#
#24
1#
b01101101 )
b01101110 *
#25
0#
#26
1#
b01101111 *
#27
0#
#28
1#
b01101101 *
#29
0#
#30
1#
b01101100 )
#31
0#
#32
1#
b01101110 )
#33
0#
#34
1#
b01110001 )
b01101100 *
#35
0#
#36
1#
b01101110 )
b01101110 *
#37
0#
#38
1#
b01101101 )
b01110001 *
#39
0#
#40
1#
b01101100 )
b01101110 *
#41
0#
#42
1#
b01101011 )
b01101101 *
#43
0#
#44
1#
b01101100 )
b01101100 *
#45
0#
#46
1#
b01101111 )
b01101011 *
#47
0#
#48
1#
b01101100 *
#49
0#
#50
1#
b01101101 )
b01101111 *
#51
0#
#52
1#
#53
0#
#54
1#
b01101110 )
b01101101 *
#55
0#
#56
1#
b01101010 )
#57
0#
#58
1#
b01101111 )
b01101110 *
#59
0#
#60
1#
b01101010 *
#61
0#
#62
1#
b01101100 )
b01101111 *
#63
0#
#64
1#
b01101110 )
#65
0#
#66
1#
b01101100 *
#67
0#
#68
1#
b01101110 *
#69
0#
#70
1#
b01101111 )
#71
0#
#72
1#
b01101110 )
#73
0#
#74
1#
b01110011 )
b01101111 *
#75
0#
#76
1#
b01101110 )
b01101110 *
#77
0#
#78
1#
b01110001 )
b01110011 *
#79
0#
#80
1#
b01101110 *
#81
0#
#82
1#
b01101111 )
b01110001 *
#83
0#
#84
1#
#85
0#
#86
1#
b01101111 *
#87
0#
#88
1#
b01110000 )
#89
0#
#90
1#
#91
0#
#92
1#
b01101111 )
b01110000 *
#93
0#
#94
1#
b01110000 )
#95
0#
#96
1#
b01101110 )
b01101111 *
#97
0#
#98
1#
b01101111 )
b01110000 *
#99
0#
#100
1#
b01101101 )
b01101110 *
#101
0#
#102
1#
b01101100 )
b01101111 *
#103
0#
#104
1#
b01101110 )
b01101101 *
#105
0#
#106
1#
b01101111 )
b01101100 *
#107
0#
#108
1#
b01110000 )
b01101110 *
#109
0#
#110
1#
b01101101 )
b01101111 *
#111
0#
#112
1#
b01101110 )
b01110000 *
#113
0#
#114
1#
b01110000 )
b01101101 *
#115
0#
#116
1#
b01101101 )
b01101110 *
#117
0#
#118
1#
b01101111 )
b01110000 *
#119
0#
#120
1#
b01101101 *
#121
0#
#122
1#
b01101110 )
b01101111 *
#123
0#
#124
1#
b01110010 )
#125
0#
#126
1#
b01110011 )
b01101110 *
#127
0#
#128
1#
b01110010 *
#129
0#
#130
1#
b01110010 )
b01110011 *
#131
0#
#132
1#
b01110011 )
#133
0#
#134
1#
b01110010 *
#135
0#
#136
1#
b01101110 )
b01110011 *
#137
0#
#138
1#
b01101111 )
#139
0#
#140
1#
b01110001 )
b01101110 *
#141
0#
#142
1#
b01101111 *
#143
0#
#144
1#
b01110000 )
b01110001 *
#145
0#
#146
1#
b01101111 )
#147
0#
#148
1#
b01110000 )
b01110000 *
#149
0#
#150
1#
b01110010 )
b01101111 *
#151
0#
#152
1#
b01110000 )
b01110000 *
#153
0#
#154
1#
b01101110 )
b01110010 *
#155
0#
#156
1#
b01110000 )
b01110000 *
#157
0#
#158
1#
b01101110 *
#159
0#
#160
1#
b01110000 *
#161
0#
#162
1#
#163
0#
#164
1#
b01101101 )
#165
0#
#166
1#
b01101110 )
#167
0#
#168
1#
b01101101 *
#169
0#
#170
1#
b01101110 *
#171
0#
#172
1#
b01101111 )
#173
0#
#174
1#
b01101101 )
#175
0#
#176
1#
b01101011 )
b01101111 *
#177
0#
#178
1#
b01101100 )
b01101101 *
#179
0#
#180
1#
b01101101 )
b01101011 *
#181
0#
#182
1#
b01101011 )
b01101100 *
#183
0#
#184
1#
b01101101 *
#185
0#
#186
1#
b01101011 *
#187
0#
#188
1#
b01101000 )
#189
0#
#190
1#
#191
0#
#192
1#
b01101010 )
b01101000 *
#193
0#
#194
1#
b01101001 )
#195
0#
#196
1#
b01101011 )
b01101010 *
#197
0#
#198
1#
b01101001 *
#199
0#
#200
1#
b01101001 )
b01101011 *
#201
0#
#202
1#
b01101010 )
#203
0#
#204
1#
b01101001 *
#205
0#
#206
1#
b01101010 *
#207
0#
#208
1#
#209
0#
#210
1#
b01101001 )
#211
0#
#212
1#
b01100110 )
#213
0#
#214
1#
b01101110 )
b01101001 *
#215
0#
#216
1#
b01101001 )
b01100110 *
#217
0#
#218
1#
b01101100 )
b01101110 *
#219
0#
#220
1#
b01101001 *
#221
0#
#222
1#
b01101110 )
b01101100 *
#223
0#
#224
1#
b01101001 )
#225
0#
#226
1#
b01101100 )
b01101110 *
#227
0#
#228
1#
b01101101 )
b01101001 *
#229
0#
#230
1#
b01101110 )
b01101100 *
#231
0#
#232
1#
b01101101 )
b01101101 *
#233
0#
#234
1#
b01101010 )
b01101110 *
#235
0#
#236
1#
b01101101 )
b01101101 *
#237
0#
#238
1#
b01101010 *
#239
0#
#240
1#
b01101101 *
#241
0#
#242
1#
b01101111 )
#243
0#
#244
1#
#245
0#
#246
1#
b01101101 )
b01101111 *
#247
0#
#248
1#
b01101111 )
#249
0#
#250
1#
b01110000 )
b01101101 *
#251
0#
#252
1#
b01101100 )
b01101111 *
#253
0#
#254
1#
b01101110 )
b01110000 *
#255
0#
#256
1#
b01101101 )
b01101100 *
#257
0#
#258
1#
b01101100 )
b01101110 *
#259
0#
#260
1#
b01101101 )
b01101101 *
#261
0#
#262
1#
b01101110 )
b01101100 *
#263
0#
#264
1#
b01101101 *
#265
0#
#266
1#
b01101111 )
b01101110 *
#267
0#
#268
1#
b01101011 )
#269
0#
#270
1#
b01101101 )
b01101111 *
#271
0#
#272
1#
b01101011 )
b01101011 *
#273
0#
#274
1#
b01101010 )
b01101101 *
#275
0#
#276
1#
b01101110 )
b01101011 *
#277
0#
#278
1#
b01101100 )
b01101010 *
#279
0#
#280
1#
b01101110 *
#281
0#
#282
1#
b01101100 *
#283
0#
#284
1#
#285
0#
#286
1#
b01101011 )
#287
0#
#288
1#
b01101100 )
#289
0#
#290
1#
b01101000 )
b01101011 *
#291
0#
#292
1#
b01100111 )
b01101100 *
#293
0#
#294
1#
b01101001 )
b01101000 *
#295
0#
#296
1#
b01101011 )
b01100111 *
#297
0#
#298
1#
b01101001 )
b01101001 *
#299
0#
#300
1#
b01101011 *
#301
0#
#302
1#
b01100111 )
b01101001 *
#303
0#
#304
1#
b01101001 )
#305
0#
#306
1#
b01101010 )
b01100111 *
#307
0#
#308
1#
b01101101 )
b01101001 *
#309
0#
#310
1#
b01101010 )
b01101010 *
#311
0#
#312
1#
b01101101 *
#313
0#
#314
1#
b01101000 )
b01101010 *
#315
0#
#316
1#
#317
0#
#318
1#
b01101001 )
b01101000 *
#319
0#
#320
1#
b01101000 )
#321
0#
#322
1#
b01100111 )
b01101001 *
#323
0#
#324
1#
b01100101 )
b01101000 *
#325
0#
#326
1#
b01101010 )
b01100111 *
#327
0#
#328
1#
b01100110 )
b01100101 *
#329
0#
#330
1#
b01101001 )
b01101010 *
#331
0#
#332
1#
b01101000 )
b01100110 *
#333
0#
#334
1#
b01101001 )
b01101001 *
#335
0#
#336
1#
b01101000 )
b01101000 *
#337
0#
#338
1#
b01101001 *
#339
0#
#340
1#
b01101001 )
b01101000 *
#341
0#
#342
1#
b01101000 )
#343
0#
#344
1#
b01101001 *
#345
0#
#346
1#
b01101011 )
b01101000 *
#347
0#
#348
1#
b01101010 )
#349
0#
#350
1#
b01101011 *
#351
0#
#352
1#
b01101000 )
b01101010 *
#353
0#
#354
1#
#355
0#
#356
1#
b01101001 )
b01101000 *
#357
0#
#358
1#
b01100110 )
#359
0#
#360
1#
b01101000 )
b01101001 *
#361
0#
#362
1#
b01101001 )
b01100110 *
#363
0#
#364
1#
b01100111 )
b01101000 *
#365
0#
#366
1#
b01101001 )
b01101001 *
#367
0#
#368
1#
b01101010 )
b01100111 *
#369
0#
#370
1#
b01101001 *
#371
0#
#372
1#
b01101000 )
b01101010 *
#373
0#
#374
1#
b01100111 )
#375
0#
#376
1#
b01101010 )
b01101000 *
#377
0#
#378
1#
b01101011 )
b01100111 *
#379
0#
#380
1#
b01101001 )
b01101010 *
#381
0#
#382
1#
b01101011 *
#383
0#
#384
1#
b01101000 )
b01101001 *
#385
0#
#386
1#
b01101010 )
#387
0#
#388
1#
b01101000 *
#389
0#
#390
1#
b01101000 )
b01101010 *
#391
0#
#392
1#
b01101010 )
#393
0#
#394
1#
b01101000 )
b01101000 *
#395
0#
#396
1#
b01101011 )
b01101010 *
#397
0#
#398
1#
b01101100 )
b01101000 *
#399
0#
#400
1#
b01101101 )
b01101011 *
#401
0#
#402
1#
b01101100 *
#403
0#
#404
1#
b01101100 )
b01101101 *
#405
0#
#406
1#
b01101011 )
#407
0#
#408
1#
b01101110 )
b01101100 *
#409
0#
#410
1#
b01101100 )
b01101011 *
#411
0#
#412
1#
b01101001 )
b01101110 *
#413
0#
#414
1#
b01101101 )
b01101100 *
#415
0#
#416
1#
b01101001 )
b01101001 *
#417
0#
#418
1#
b01101101 *
#419
0#
#420
1#
b01101101 )
b01101001 *
#421
0#
#422
1#
b01101001 )
#423
0#
#424
1#
b01101100 )
b01101101 *
#425
0#
#426
1#
b01101010 )
b01101001 *
#427
0#
#428
1#
b01101011 )
b01101100 *
#429
0#
#430
1#
b01101000 )
b01101010 *
#431
0#
#432
1#
b01101001 )
b01101011 *
#433
0#
#434
1#
b01101000 )
b01101000 *
#435
0#
#436
1#
b01101010 )
b01101001 *
#437
0#
#438
1#
b01101001 )
b01101000 *
#439
0#
#440
1#
b01101010 )
b01101010 *
#441
0#
#442
1#
b01101001 )
b01101001 *
#443
0#
#444
1#
b01101010 )
b01101010 *
#445
0#
#446
1#
b01101001 )
b01101001 *
#447
0#
#448
1#
b01101100 )
b01101010 *
#449
0#
#450
1#
b01101001 *
#451
0#
#452
1#
b01101010 )
b01101100 *
#453
0#
#454
1#
b01100111 )
#455
0#
#456
1#
b01101000 )
b01101010 *
#457
0#
#458
1#
b01101010 )
b01100111 *
#459
0#
#460
1#
b01101000 )
b01101000 *
#461
0#
#462
1#
b01101001 )
b01101010 *
#463
0#
#464
1#
b01101010 )
b01101000 *
#465
0#
#466
1#
b01101001 )
b01101001 *
#467
0#
#468
1#
b01101011 )
b01101010 *
#469
0#
#470
1#
b01101001 )
b01101001 *
#471
0#
#472
1#
b01101011 *
#473
0#
#474
1#
b01101001 *
#475
0#
#476
1#
#477
0#
#478
1#
#479
0#
#480
1#
b01100110 )
#481
0#
#482
1#
b01100111 )
#483
0#
#484
1#
b01100110 *
#485
0#
#486
1#
b01101000 )
b01100111 *
#487
0#
#488
1#
b01101001 )
#489
0#
#490
1#
b01101000 )
b01101000 *
#491
0#
#492
1#
b01101001 *
#493
0#
#494
1#
b01101000 *
#495
0#
#496
1#
b01101001 )
#497
0#
#498
1#
b01101011 )
#499
0#
#500
1#
b01101001 )
b01101001 *
#501
0#
#502
1#
b01101011 *
#503
0#
#504
1#
b01101001 *
#505
0#
#506
1#
b01101011 )
#507
0#
#508
1#
b01101010 )
#509
0#
#510
1#
b01101011 )
b01101011 *
#511
0#
#512
1#
b01101001 )
b01101010 *
#513
0#
#514
1#
b01101011 *
#515
0#
#516
1#
b01101100 )
b01101001 *
#517
0#
#518
1#
b01101011 )
#519
0#
#520
1#
b01101101 )
b01101100 *
#521
0#
#522
1#
b01101111 )
b01101011 *
#523
0#
#524
1#
b01101101 *
#525
0#
#526
1#
b01101101 )
b01101111 *
#527
0#
#528
1#
#529
0#
#530
1#
b01101101 *
#531
0#
#532
1#
b01101110 )
#533
0#
#534
1#
#535
0#
#536
1#
b01101111 )
b01101110 *
#537
0#
#538
1#
b01110001 )
#539
0#
#540
1#
b01101110 )
b01101111 *
#541
0#
#542
1#
b01110000 )
b01110001 *
#543
0#
#544
1#
b01101101 )
b01101110 *
#545
0#
#546
1#
b01110000 *
#547
0#
#548
1#
b01110010 )
b01101101 *
#549
0#
#550
1#
b01110001 )
#551
0#
#552
1#
b01101101 )
b01110010 *
#553
0#
#554
1#
b01101110 )
b01110001 *
#555
0#
#556
1#
b01110000 )
b01101101 *
#557
0#
#558
1#
b01101110 )
b01101110 *
#559
0#
#560
1#
b01110000 )
b01110000 *
#561
0#
#562
1#
b01101111 )
b01101110 *
#563
0#
#564
1#
b01101110 )
b01110000 *
#565
0#
#566
1#
b01101010 )
b01101111 *
#567
0#
#568
1#
b01101100 )
b01101110 *
#569
0#
#570
1#
b01101110 )
b01101010 *
#571
0#
#572
1#
b01101101 )
b01101100 *
#573
0#
#574
1#
b01110000 )
b01101110 *
#575
0#
#576
1#
b01110001 )
b01101101 *
#577
0#
#578
1#
b01110000 *
#579
0#
#580
1#
b01110000 )
b01110001 *
#581
0#
#582
1#
b01101111 )
#583
0#
#584
1#
b01110000 *
#585
0#
#586
1#
b01101110 )
b01101111 *
#587
0#
#588
1#
#589
0#
#590
1#
b01101101 )
b01101110 *
#591
0#
#592
1#
b01101111 )
#593
0#
#594
1#
b01101101 )
b01101101 *
#595
0#
#596
1#
b01101110 )
b01101111 *
#597
0#
#598
1#
b01101101 *
#599
0#
#600
1#
b01110001 )
b01101110 *
#601
0#
#602
1#
b01101111 )
#603
0#
#604
1#
b01110001 )
b01110001 *
#605
0#
#606
1#
b01110010 )
b01101111 *
#607
0#
#608
1#
b01110001 )
b01110001 *
#609
0#
#610
1#
b01110010 *
#611
0#
#612
1#
b01110000 )
b01110001 *
#613
0#
#614
1#
b01110010 )
#615
0#
#616
1#
b01110001 )
b01110000 *
#617
0#
#618
1#
b01110010 *
#619
0#
#620
1#
b01110000 )
b01110001 *
#621
0#
#622
1#
#623
0#
#624
1#
b01101111 )
b01110000 *
#625
0#
#626
1#
#627
0#
#628
1#
b01110001 )
b01101111 *
#629
0#
#630
1#
b01101111 )
#631
0#
#632
1#
b01110010 )
b01110001 *
#633
0#
#634
1#
b01110001 )
b01101111 *
#635
0#
#636
1#
b01110010 )
b01110010 *
#637
0#
#638
1#
b01110000 )
b01110001 *
#639
0#
#640
1#
b01101111 )
b01110010 *
#641
0#
#642
1#
b01110001 )
b01110000 *
#643
0#
#644
1#
b01110000 )
b01101111 *
#645
0#
#646
1#
b01110010 )
b01110001 *
#647
0#
#648
1#
b01101111 )
b01110000 *
#649
0#
#650
1#
b01110001 )
b01110010 *
#651
0#
#652
1#
b01101111 )
b01101111 *
#653
0#
#654
1#
b01101101 )
b01110001 *
#655
0#
#656
1#
b01101111 )
b01101111 *
#657
0#
#658
1#
b01101110 )
b01101101 *
#659
0#
#660
1#
b01110001 )
b01101111 *
#661
0#
#662
1#
b01101101 )
b01101110 *
#663
0#
#664
1#
b01110001 )
b01110001 *
#665
0#
#666
1#
b01110010 )
b01101101 *
#667
0#
#668
1#
b01110001 *
#669
0#
#670
1#
b01101111 )
b01110010 *
#671
0#
#672
1#
b01110000 )
#673
0#
#674
1#
b01110100 )
b01101111 *
#675
0#
#676
1#
b01110011 )
b01110000 *
#677
0#
#678
1#
b01110010 )
b01110100 *
#679
0#
#680
1#
b01110011 *
#681
0#
#682
1#
b01110001 )
b01110010 *
#683
0#
#684
1#
b01110010 )
#685
0#
#686
1#
b01101111 )
b01110001 *
#687
0#
#688
1#
b01110011 )
b01110010 *
#689
0#
#690
1#
b01110010 )
b01101111 *
#691
0#
#692
1#
b01110011 )
b01110011 *
#693
0#
#694
1#
b01101111 )
b01110010 *
#695
0#
#696
1#
b01110001 )
b01110011 *
#697
0#
#698
1#
b01101111 *
#699
0#
#700
1#
b01110011 )
b01110001 *
#701
0#
#702
1#
#703
0#
#704
1#
b01110010 )
b01110011 *
#705
0#
#706
1#
b01110011 )
#707
0#
#708
1#
b01110010 )
b01110010 *
#709
0#
#710
1#
b01110000 )
b01110011 *
#711
0#
#712
1#
b01110001 )
b01110010 *
#713
0#
#714
1#
b01110000 *
#715
0#
#716
1#
b01101111 )
b01110001 *
#717
0#
#718
1#
b01110000 )
#719
0#
#720
1#
b01101111 )
b01101111 *
#721
0#
#722
1#
b01110000 )
b01110000 *
#723
0#
#724
1#
b01101110 )
b01101111 *
#725
0#
#726
1#
b01101111 )
b01110000 *
#727
0#
#728
1#
b01110000 )
b01101110 *
#729
0#
#730
1#
b01101110 )
b01101111 *
#731
0#
#732
1#
b01110001 )
b01110000 *
#733
0#
#734
1#
b01101110 )
b01101110 *
#735
0#
#736
1#
b01110010 )
b01110001 *
#737
0#
#738
1#
b01101111 )
b01101110 *
#739
0#
#740
1#
b01110000 )
b01110010 *
#741
0#
#742
1#
b01101111 *
#743
0#
#744
1#
b01110010 )
b01110000 *
#745
0#
#746
1#
b01101111 )
#747
0#
#748
1#
b01101110 )
b01110010 *
#749
0#
#750
1#
b01101111 *
#751
0#
#752
1#
b01101100 )
b01101110 *
#753
0#
#754
1#
b01101101 )
#755
0#
#756
1#
b01101110 )
b01101100 *
#757
0#
#758
1#
b01110000 )
b01101101 *
#759
0#
#760
1#
b01101110 )
b01101110 *
#761
0#
#762
1#
b01110000 *
#763
0#
#764
1#
b01101111 )
b01101110 *
#765
0#
#766
1#
b01101101 )
#767
0#
#768
1#
b01101110 )
b01101111 *
#769
0#
#770
1#
b01101101 )
b01101101 *
#771
0#
#772
1#
b01101010 )
b01101110 *
#773
0#
#774
1#
b01101101 )
b01101101 *
#775
0#
#776
1#
b01101010 *
#777
0#
#778
1#
b01110010 )
b01101101 *
#779
0#
#780
1#
b01101111 )
#781
0#
#782
1#
b01101110 )
b01110010 *
#783
0#
#784
1#
b01101011 )
b01101111 *
#785
0#
#786
1#
b01101100 )
b01101110 *
#787
0#
#788
1#
b01101111 )
b01101011 *
#789
0#
#790
1#
b01101101 )
b01101100 *
#791
0#
#792
1#
b01101111 *
#793
0#
#794
1#
b01101100 )
b01101101 *
#795
0#
#796
1#
b01101110 )
#797
0#
#798
1#
b01101101 )
b01101100 *
#799
0#
#800
1#
b01101100 )
b01101110 *
#801
0#
#802
1#
b01101011 )
b01101101 *
#803
0#
#804
1#
b01101101 )
b01101100 *
#805
0#
#806
1#
b01101111 )
b01101011 *
#807
0#
#808
1#
b01110000 )
b01101101 *
#809
0#
#810
1#
b01101111 *
#811
0#
#812
1#
b01101110 )
b01110000 *
#813
0#
#814
1#
b01101111 )
#815
0#
#816
1#
b01101110 *
#817
0#
#818
1#
b01110001 )
b01101111 *
#819
0#
#820
1#
b01101111 )
#821
0#
#822
1#
b01101010 )
b01110001 *
#823
0#
#824
1#
b01101110 )
b01101111 *
#825
0#
#826
1#
b01101010 *
#827
0#
#828
1#
b01101110 *
#829
0#
#830
1#
b01101101 )
#831
0#
#832
1#
b01101010 )
#833
0#
#834
1#
b01101011 )
b01101101 *
#835
0#
#836
1#
b01101010 )
b01101010 *
#837
0#
#838
1#
b01101100 )
b01101011 *
#839
0#
#840
1#
b01101001 )
b01101010 *
#841
0#
#842
1#
b01101100 *
#843
0#
#844
1#
b01101010 )
b01101001 *
#845
0#
#846
1#
#847
0#
#848
1#
b01101010 *
#849
0#
#850
1#
b01101001 )
#851
0#
#852
1#
#853
0#
#854
1#
b01101010 )
b01101001 *
#855
0#
#856
1#
b01100111 )
#857
0#
#858
1#
b01101010 )
b01101010 *
#859
0#
#860
1#
b01100111 *
#861
0#
#862
1#
b01101010 *
#863
0#
#864
1#
b01101000 )
#865
0#
#866
1#
b01101001 )
#867
0#
#868
1#
b01101000 *
#869
0#
#870
1#
b01101011 )
b01101001 *
#871
0#
#872
1#
b01101010 )
#873
0#
#874
1#
b01101011 )
b01101011 *
#875
0#
#876
1#
b01101010 *
#877
0#
#878
1#
b01101001 )
b01101011 *
#879
0#
#880
1#
b01101011 )
#881
0#
#882
1#
b01101001 )
b01101001 *
#883
0#
#884
1#
b01101010 )
b01101011 *
#885
0#
#886
1#
b01101011 )
b01101001 *
#887
0#
#888
1#
b01101010 *
#889
0#
#890
1#
b01100111 )
b01101011 *
#891
0#
#892
1#
b01101001 )
#893
0#
#894
1#
b01100111 *
#895
0#
#896
1#
b01101010 )
b01101001 *
#897
0#
#898
1#
b01101000 )
#899
0#
#900
1#
b01101010 )
b01101010 *
#901
0#
#902
1#
b01100111 )
b01101000 *
#903
0#
#904
1#
b01101011 )
b01101010 *
#905
0#
#906
1#
b01101000 )
b01100111 *
#907
0#
#908
1#
b01101010 )
b01101011 *
#909
0#
#910
1#
b01101001 )
b01101000 *
#911
0#
#912
1#
b01101010 )
b01101010 *
#913
0#
#914
1#
b01101001 *
#915
0#
#916
1#
b01101011 )
b01101010 *
#917
0#
#918
1#
b01101100 )
#919
0#
#920
1#
b01101011 *
#921
0#
#922
1#
b01101011 )
b01101100 *
#923
0#
#924
1#
#925
0#
#926
1#
b01101000 )
b01101011 *
#927
0#
#928
1#
b01101011 )
#929
0#
#930
1#
b01101100 )
b01101000 *
#931
0#
#932
1#
b01101101 )
b01101011 *
#933
0#
#934
1#
b01101001 )
b01101100 *
#935
0#
#936
1#
b01100110 )
b01101101 *
#937
0#
#938
1#
b01101100 )
b01101001 *
#939
0#
#940
1#
b01101010 )
b01100110 *
#941
0#
#942
1#
b01101100 )
b01101100 *
#943
0#
#944
1#
b01101001 )
b01101010 *
#945
0#
#946
1#
b01101100 *
#947
0#
#948
1#
b01101000 )
b01101001 *
#949
0#
#950
1#
b01101010 )
#951
0#
#952
1#
b01101100 )
b01101000 *
#953
0#
#954
1#
b01101010 )
b01101010 *
#955
0#
#956
1#
b01101100 )
b01101100 *
#957
0#
#958
1#
b01101010 )
b01101010 *
#959
0#
#960
1#
b01101100 *
#961
0#
#962
1#
b01101011 )
b01101010 *
#963
0#
#964
1#
b01101010 )
#965
0#
#966
1#
b01101001 )
b01101011 *
#967
0#
#968
1#
b01101010 *
#969
0#
#970
1#
b01101000 )
b01101001 *
#971
0#
#972
1#
b01101001 )
#973
0#
#974
1#
b01101010 )
b01101000 *
#975
0#
#976
1#
b01101001 )
b01101001 *
#977
0#
#978
1#
b01101010 )
b01101010 *
#979
0#
#980
1#
b01101100 )
b01101001 *
#981
0#
#982
1#
b01101011 )
b01101010 *
#983
0#
#984
1#
b01101100 )
b01101100 *
#985
0#
#986
1#
b01101011 *
#987
0#
#988
1#
b01101010 )
b01101100 *
#989
0#
#990
1#
b01101001 )
#991
0#
#992
1#
b01101010 )
b01101010 *
#993
0#
#994
1#
b01101100 )
b01101001 *
#995
0#
#996
1#
b01101010 )
b01101010 *
#997
0#
#998
1#
b01101001 )
b01101100 *
#999
0#
#1000
1#
b01101000 )
b01101010 *
#1001
0#
#1002
1#
b01100111 )
b01101001 *
#1003
0#
#1004
1#
b01101001 )
b01101000 *
#1005
0#
#1006
1#
b01101100 )
b01100111 *
#1007
0#
#1008
1#
b01101001 )
b01101001 *
#1009
0#
#1010
1#
b01101010 )
b01101100 *
#1011
0#
#1012
1#
b01101000 )
b01101001 *
#1013
0#
#1014
1#
b01101010 )
b01101010 *
#1015
0#
#1016
1#
b01101000 )
b01101000 *
#1017
0#
#1018
1#
b01101011 )
b01101010 *
#1019
0#
#1020
1#
b01101100 )
b01101000 *
#1021
0#
#1022
1#
b01101101 )
b01101011 *
#1023
0#
#1024
1#
b01101010 )
b01101100 *
#1025
0#
#1026
1#
b01101111 )
b01101101 *
#1027
0#
#1028
1#
b01101010 *
#1029
0#
#1030
1#
b01110001 )
b01101111 *
#1031
0#
#1032
1#
b01101101 )
#1033
0#
#1034
1#
b01101111 )
b01110001 *
#1035
0#
#1036
1#
b01110010 )
b01101101 *
#1037
0#
#1038
1#
b01101111 *
#1039
0#
#1040
1#
b01110001 )
b01110010 *
#1041
0#
#1042
1#
b01101101 )
#1043
0#
#1044
1#
b01110001 *
#1045
0#
#1046
1#
b01101111 )
b01101101 *
#1047
0#
#1048
1#
b01101101 )
#1049
0#
#1050
1#
b01101100 )
b01101111 *
#1051
0#
#1052
1#
b01101101 *
#1053
0#
#1054
1#
b01101101 )
b01101100 *
#1055
0#
#1056
1#
#1057
0#
#1058
1#
b01101100 )
b01101101 *
#1059
0#
#1060
1#
b01101011 )
#1061
0#
#1062
1#
b01101001 )
b01101100 *
#1063
0#
#1064
1#
b01101011 *
#1065
0#
#1066
1#
b01101001 *
#1067
0#
#1068
1#
b01100111 )
#1069
0#
#1070
1#
b01101000 )
#1071
0#
#1072
1#
b01100110 )
b01100111 *
#1073
0#
#1074
1#
b01100111 )
b01101000 *
#1075
0#
#1076
1#
b01100110 )
b01100110 *
#1077
0#
#1078
1#
b01100111 )
b01100111 *
#1079
0#
#1080
1#
b01101000 )
b01100110 *
#1081
0#
#1082
1#
b01100111 )
b01100111 *
#1083
0#
#1084
1#
b01100101 )
b01101000 *
#1085
0#
#1086
1#
b01100111 *
#1087
0#
#1088
1#
b01100100 )
b01100101 *
#1089
0#
#1090
1#
b01100110 )
#1091
0#
#1092
1#
b01100101 )
b01100100 *
#1093
0#
#1094
1#
b01100100 )
b01100110 *
#1095
0#
#1096
1#
b01100011 )
b01100101 *
#1097
0#
#1098
1#
b01100101 )
b01100100 *
#1099
0#
#1100
1#
b01100011 )
b01100011 *
#1101
0#
#1102
1#
b01100110 )
b01100101 *
#1103
0#
#1104
1#
b01100011 *
#1105
0#
#1106
1#
b01100101 )
b01100110 *
#1107
0#
#1108
1#
#1109
0#
#1110
1#
b01100100 )
b01100101 *
#1111
0#
#1112
1#
#1113
0#
#1114
1#
b01100010 )
b01100100 *
#1115
0#
#1116
1#
b01100011 )
#1117
0#
#1118
1#
b01100001 )
b01100010 *
#1119
0#
#1120
1#
b01100110 )
b01100011 *
#1121
0#
#1122
1#
b01100101 )
b01100001 *
#1123
0#
#1124
1#
b01100011 )
b01100110 *
#1125
0#
#1126
1#
b01100100 )
b01100101 *
#1127
0#
#1128
1#
b01101000 )
b01100011 *
#1129
0#
#1130
1#
b01100101 )
b01100100 *
#1131
0#
#1132
1#
b01100110 )
b01101000 *
#1133
0#
#1134
1#
b01100101 )
b01100101 *
#1135
0#
