task1/rom.sv
module rom #(
    parameter ADDRESS_WIDTH = 8,
                DATA_WIDTH = 8
) (
    input logic             clk,
    input logic         [ADDRESS_WIDTH-1:0] addr,  
    output logic        [DATA_WIDTH-1:0] dout,
);

logic [DATA_WIDTH-1:0] rom_array [2**ADDRESS_WIDTH-1:0];

initial begin
    $display("Loading rom");
    $readmemh("sinerom.mem", rom_array);
end;

always_ff @(posedge clk)
    dout <= rom_array[addr];


endmodule

task2/counter.sv
module counter #(
    parameter WIDTH = 8
)(
    input logic clk,
    input logic rst, 
    input logic en,
    input logic [WIDTH-1:0] incr,
    output logic [WIDTH-1:0] count
);

always @ (posedge clk, posedge rst)
    if (rst)
        count <= {WIDTH{1'b0}};
    else if(en) 
        count <= count + 1'b1;


endmodule

task1/sinegen.sv
module sinegen #(
    parameter A_WIDTH = 8,
              D_WIDTH = 8
)(
    input logic     clk,
    input logic     rst,
    input logic     en,
    input logic [D_WIDTH-1:0] incr,
    output logic [D_WIDTH-1:0] dout
);

logic [A_WIDTH-1:0] address;


counter counter (
    .clk (clk),
    .rst (rst),
    .en (en),
    .incr (incr),
    .count (address)
);

rom sinerom (
    .clk(clk),
    .addr (address),
    .dout (dout),
);

endmodule

task2/top.vcd
$version Generated by VerilatedVcd $end
$date Thu Oct 24 10:46:19 2024 $end
$timescale 1ps $end

 $scope module TOP $end
  $var wire  1 # clk $end
  $var wire  8 ' dout [7:0] $end
  $var wire  1 % en $end
  $var wire  8 & incr [7:0] $end
  $var wire  1 $ rst $end
  $scope module sinegen $end
   $var wire 32 ) A_WIDTH [31:0] $end
   $var wire 32 ) D_WIDTH [31:0] $end
   $var wire  8 ( address [7:0] $end
   $var wire  1 # clk $end
   $var wire  8 ' dout [7:0] $end
   $var wire  1 % en $end
   $var wire  8 & incr [7:0] $end
   $var wire  1 $ rst $end
   $scope module counter $end
    $var wire 32 ) WIDTH [31:0] $end
    $var wire  1 # clk $end
    $var wire  8 ( count [7:0] $end
    $var wire  1 % en $end
    $var wire  8 & incr [7:0] $end
    $var wire  1 $ rst $end
   $upscope $end
   $scope module sinerom $end
    $var wire 32 ) ADDRESS_WIDTH [31:0] $end
    $var wire 32 ) DATA_WIDTH [31:0] $end
    $var wire  8 ( addr [7:0] $end
    $var wire  1 # clk $end
    $var wire  8 ' dout [7:0] $end
   $upscope $end
  $upscope $end
 $upscope $end
$enddefinitions $end


#0
1#
0$
1%
b00000100 &
b00000000 '
b00000000 (
b00000000000000000000000000001000 )
#1
0#
#2
1#
b11111110 '
b00000100 (
#3
0#
#4
1#
b11111101 '
b00001000 (
#5
0#
#6
1#
b11111011 '
b00001100 (
#7
0#
#8
1#
b11111000 '
b00010000 (
#9
0#
#10
1#
b11110100 '
b00010100 (
#11
0#
#12
1#
b11101111 '
b00011000 (
#13
0#
#14
1#
b11101000 '
b00011100 (
#15
0#
#16
1#
b11100001 '
b00100000 (
#17
0#
#18
1#
b11011000 '
b00100100 (
#19
0#
#20
1#
b11001111 '
b00101000 (
#21
0#
#22
1#
b11000101 '
b00101100 (
#23
0#
#24
1#
b10111010 '
b00110000 (
#25
0#
#26
1#
b10101111 '
b00110100 (
#27
0#
#28
1#
b10100011 '
b00111000 (
#29
0#
#30
1#
b10010111 '
b00111100 (
#31
0#
#32
1#
b10001011 '
b01000000 (
#33
0#
#34
1#
b01111110 '
b01000100 (
#35
0#
#36
1#
b01110010 '
b01001000 (
#37
0#
#38
1#
b01100110 '
b01001100 (
#39
0#
#40
1#
b01011010 '
b01010000 (
#41
0#
#42
1#
b01001110 '
b01010100 (
#43
0#
#44
1#
b01000011 '
b01011000 (
#45
0#
#46
1#
b00111000 '
b01011100 (
#47
0#
#48
1#
b00101110 '
b01100000 (
#49
0#
#50
1#
b00100101 '
b01100100 (
#51
0#
#52
1#
b00011100 '
b01101000 (
#53
0#
#54
1#
b00010101 '
b01101100 (
#55
0#
#56
1#
b00001110 '
b01110000 (
#57
0#
#58
1#
b00001001 '
b01110100 (
#59
0#
#60
1#
b00000101 '
b01111000 (
#61
0#
#62
1#
b00000010 '
b01111100 (
#63
0#
#64
1#
b00000000 '
b10000000 (
#65
0#
b00000011 &
#66
1#
b10000011 (
#67
0#
#68
1#
b10000110 (
#69
0#
#70
1#
b00000010 &
b00000001 '
b10001001 (
#71
0#
#72
1#
b00000011 '
b10001011 (
#73
0#
b00000001 &
#74
1#
b00000100 '
b10001100 (
#75
0#
#76
1#
b00000101 '
b10001101 (
#77
0#
#78
1#
b00000110 '
b10001110 (
#79
0#
#80
1#
b00000111 '
b10001111 (
#81
0#
#82
1#
b00001000 '
b10010000 (
#83
0#
#84
1#
b00001001 '
b10010001 (
#85
0#
#86
1#
b00000000 &
b00001010 '
b10010010 (
#87
0#
#88
1#
b00001100 '
